tgalert/__init__.py
tgalert/tgalert.py
Telegram_Alert-1.0.4.dist-info/METADATA
Telegram_Alert-1.0.4.dist-info/WHEEL
Telegram_Alert-1.0.4.dist-info/top_level.txt
Telegram_Alert-1.0.4.dist-info/RECORD
