Metadata-Version: 2.1
Name: Telegram-Alert
Version: 1.0.4
Summary: Library for sending error messages to Telegram
Home-page: https://github.com/arsen671games3/tgalert
Author: Arsen
Author-email: arsen.dev@arsen.me
Keywords: telegram alert library python
Requires-Python: ~=3.7
